chin_dict/__init__.py
chin_dict/__main__.py
chin_dict/chin_dict.py
chin_dict/chindict.py
chin_dict/main.py
chin_dict/classes/__init__.py
chin_dict/classes/charresult.py
chin_dict/classes/models.py
chin_dict/errors/NotFound.py
chin_dict/errors/__init__.py
chin_dict/helpers/__init__.py
chin_dict/helpers/cleaner.py
chin_dict/helpers/converter.py
chin_dict-0.1.3.data/data/data/hanlearn.db
tests/__init__.py
tests/test_dict.py
chin_dict-0.1.3.dist-info/LICENSE
chin_dict-0.1.3.dist-info/METADATA
chin_dict-0.1.3.dist-info/WHEEL
chin_dict-0.1.3.dist-info/entry_points.txt
chin_dict-0.1.3.dist-info/top_level.txt
chin_dict-0.1.3.dist-info/RECORD
