Metadata-Version: 2.1
Name: chin-dict
Version: 0.1.3
Summary: Mandarin dictionary
Home-page: UNKNOWN
Author: Me
License: MIT
Platform: UNKNOWN
Requires-Dist: SQLAlchemy (==1.3.22)
Requires-Dist: treelib (==1.6.1)
